numero_a_letras/__init__.py
numero_a_letras/main.py
numero_a_letras-0.0.5.dist-info/LICENSE
numero_a_letras-0.0.5.dist-info/METADATA
numero_a_letras-0.0.5.dist-info/WHEEL
numero_a_letras-0.0.5.dist-info/top_level.txt
numero_a_letras-0.0.5.dist-info/RECORD
