Metadata-Version: 2.1
Name: numero_a_letras
Version: 0.0.5
Summary: Convierte un número a letras en español
Home-page: https://github.com/lugezz/numero_a_letras_literal
Author: Eugenio
Author-email: coding_with@eugeniovazquez.com.ar
License: MIT
Classifier: License :: OSI Approved :: MIT License
Classifier: Programming Language :: Python :: 3.10
Classifier: Operating System :: OS Independent
Requires-Python: >=3.10, <3.13
License-File: LICENSE
Provides-Extra: dev
Requires-Dist: twine >=4.0.2 ; extra == 'dev'
